{"bowlingSummary":[{"match":" Vs ","bowlingTeam":"","bowlerName":"Trent Boult","overs":"10","maiden":"0","runs":"86","wickets":"1","economy":"8.60","0s":"26","4s":"9","6s":"4","wides":"2","noBalls":"0"},{"match":" Vs ","bowlingTeam":"","bowlerName":"Tim Southee","overs":"10","maiden":"0","runs":"100","wickets":"3","economy":"10.00","0s":"20","4s":"8","6s":"6","wides":"1","noBalls":"0"},{"match":" Vs ","bowlingTeam":"","bowlerName":"Mitchell Santner","overs":"10","maiden":"1","runs":"51","wickets":"0","economy":"5.10","0s":"29","4s":"3","6s":"2","wides":"0","noBalls":"0"},{"match":" Vs ","bowlingTeam":"","bowlerName":"Lockie Ferguson","overs":"8","maiden":"0","runs":"65","wickets":"0","economy":"8.12","0s":"15","4s":"7","6s":"1","wides":"1","noBalls":"0"},{"match":" Vs ","bowlingTeam":"","bowlerName":"Rachin Ravindra","overs":"7","maiden":"0","runs":"60","wickets":"0","economy":"8.57","0s":"13","4s":"2","6s":"4","wides":"2","noBalls":"0"},{"match":" Vs ","bowlingTeam":"","bowlerName":"Glenn Phillips","overs":"5","maiden":"0","runs":"33","wickets":"0","economy":"6.60","0s":"11","4s":"1","6s":"2","wides":"0","noBalls":"0"},{"match":" Vs ","bowlingTeam":"","bowlerName":"Jasprit Bumrah","overs":"10","maiden":"1","runs":"64","wickets":"1","economy":"6.40","0s":"32","4s":"6","6s":"1","wides":"6","noBalls":"0"},{"match":" Vs ","bowlingTeam":"","bowlerName":"Mohammed Siraj","overs":"9","maiden":"0","runs":"78","wickets":"1","economy":"8.66","0s":"26","4s":"10","6s":"3","wides":"3","noBalls":"0"},{"match":" Vs ","bowlingTeam":"","bowlerName":"Mohammed Shami","overs":"9.5","maiden":"0","runs":"57","wickets":"7","economy":"5.79","0s":"37","4s":"3","6s":"4","wides":"2","noBalls":"0"},{"match":" Vs ","bowlingTeam":"","bowlerName":"Ravindra Jadeja","overs":"10","maiden":"0","runs":"63","wickets":"0","economy":"6.30","0s":"29","4s":"3","6s":"3","wides":"0","noBalls":"1"},{"match":" Vs ","bowlingTeam":"","bowlerName":"Kuldeep Yadav","overs":"10","maiden":"0","runs":"56","wickets":"1","economy":"5.60","0s":"26","4s":"6","6s":"0","wides":"0","noBalls":"0"}]}